bilibili_rater/__init__.py
bilibili_rater/bilibili_rater.py
bilibili_rater/cache.py
bilibili_rater/exceptions.py
bilibili_rater/handler.py
bilibili_rater/_internal/__init__.py
bilibili_rater/_internal/bilibili/__init__.py
bilibili_rater/_internal/bilibili/bilibili_comment.py
bilibili_rater/_internal/bilibili/bilibili_fetcher.py
bilibili_rater/_internal/imdb/__init__.py
bilibili_rater/_internal/imdb/fetch_imdb.py
bilibili_rater/_internal/imdb/imdbinfo_fetcher.py
bilibili_rater-0.1.3rc1.dist-info/METADATA
bilibili_rater-0.1.3rc1.dist-info/WHEEL
bilibili_rater-0.1.3rc1.dist-info/licenses/LICENSE
bilibili_rater-0.1.3rc1.dist-info/RECORD
