Metadata-Version: 2.4
Name: bilibili-rater
Version: 0.1.3rc1
Summary: 为在Bilibili上的影视资源自动获取imdb评分
Project-URL: Homepage, https://github.com/NearlyHeadlessJack/bilibili-rater
Author-email: Jack Wang <wang@rjack.cn>
License:                     GNU GENERAL PUBLIC LICENSE
License-File: LICENSE
Classifier: License :: OSI Approved :: GNU General Public License v3 (GPLv3)
Classifier: Natural Language :: Chinese (Simplified)
Classifier: Programming Language :: Python :: 3 :: Only
Classifier: Programming Language :: Python :: 3.10
Classifier: Programming Language :: Python :: 3.11
Classifier: Programming Language :: Python :: 3.12
Classifier: Programming Language :: Python :: 3.13
Classifier: Programming Language :: Python :: 3.14
Classifier: Programming Language :: Python :: 3.15
Classifier: Topic :: Communications
Classifier: Topic :: Utilities
Requires-Python: >=3.10
Requires-Dist: bilibili-api-python>=17.4.1
Requires-Dist: httpx>=0.28.1
Requires-Dist: imdbinfo>=0.7.0
Requires-Dist: pytz>=2025.2
Requires-Dist: requests>=2.32.5
